[
    {
        "q1": "who is going to be on the roster for spain this year?",
        "a1": "may be pique",
        "kgER1": {
            "spain": [
                "coach",
                "captain",
                "world cup appearance",
                "number of world cup champion",
                "world cup Champions",
                "goalkeeper",
                "has player",
                "defender",
                "midfielder",
                "forward"
            ]
        },
        "a1_skt": "may be pique",
        "a1_v2": "may be pique",
        "corr_rel1": "",
        "obj1": "",
        "input_ent1": "spain"
    },
    {
        "q2": "did any players from spanish national team retire after this year's world cup? ",
        "a2": "yes the captain, iniesta.",
        "kgER2": {
            "spain": [
                "coach",
                "captain",
                "world cup appearance",
                "number of world cup champion",
                "world cup Champions",
                "goalkeeper",
                "has player",
                "defender",
                "midfielder",
                "forward"
            ]
        },
        "a2_skt": "yes the @relation iniesta.",
        "a2_v2": "yes the captain, iniesta.",
        "corr_rel2": "",
        "obj2": "",
        "input_ent2": "andres guardado"
    },
    {
        "q3": "how many world cups has spain won so far?",
        "a3": "i believe they only won once. ",
        "kgER3": {
            "spain": [
                "coach",
                "captain",
                "world cup appearance",
                "number of world cup champion",
                "world cup Champions",
                "goalkeeper",
                "has player",
                "defender",
                "midfielder",
                "forward"
            ]
        },
        "a3_skt": "i believe they only won once. ",
        "a3_v2": "i believe they only won once. ",
        "corr_rel3": "",
        "obj3": "",
        "input_ent3": "spain"
    },
    {
        "q4": "do they have a chance of winning the next world cup?",
        "a4": "they will be one of the favorites for sure.",
        "kgER4": {
            "spain": [
                "coach",
                "captain",
                "world cup appearance",
                "number of world cup champion",
                "world cup Champions",
                "goalkeeper",
                "has player",
                "defender",
                "midfielder",
                "forward"
            ]
        },
        "a4_skt": "they will be one of the favorites for sure.",
        "a4_v2": "they will be one of the favorites for sure.",
        "corr_rel4": "",
        "obj4": "",
        "input_ent4": "estadio do dragaoporto, portugal"
    },
    {
        "q5": "will they change the manager at the very last minute again?",
        "a5": "probably not, it didn't work out very well last time",
        "kgER5": {
            "spain": [
                "coach",
                "captain",
                "world cup appearance",
                "number of world cup champion",
                "world cup Champions",
                "goalkeeper",
                "has player",
                "defender",
                "midfielder",
                "forward"
            ]
        },
        "a5_skt": "probably not, it didn't work out very well last time",
        "a5_v2": "probably not, it didn't work out very well last time",
        "corr_rel5": "",
        "obj5": "",
        "input_ent5": "andres guardado"
    }
]