[
    {
        "q1": "i completely love brazil",
        "a1": "brazil might have lost this time, but they are still the best in the world.",
        "kgER1": {
            "brazil": [
                "coach",
                "captain",
                "world cup appearance",
                "number of world cup champion",
                "world cup Champions",
                "goalkeeper",
                "has player",
                "defender",
                "midfielder",
                "forward"
            ]
        },
        "a1_skt": "@entity might have lost this time, but they are still the best in the world.",
        "a1_v2": "brazil might have lost this time, but they are still the best in the world.",
        "corr_rel1": "",
        "obj1": "",
        "input_ent1": "brazil"
    },
    {
        "q2": "yeah, they lost to belgium on a fluke own goal. they would have won the cup otherwise.",
        "a2": "they played really bad, no excuse from that.",
        "kgER2": {
            "brazil": [
                "coach",
                "captain",
                "world cup appearance",
                "number of world cup champion",
                "world cup Champions",
                "goalkeeper",
                "has player",
                "defender",
                "midfielder",
                "forward"
            ],
            "belgium": [
                "coach",
                "captain",
                "world cup appearance",
                "number of world cup champion",
                "world cup Third place",
                "goalkeeper",
                "has player",
                "defender",
                "midfielder",
                "forward"
            ]
        },
        "a2_skt": "they played really bad, no excuse from that.",
        "a2_v2": "they played really bad, no excuse from that.",
        "corr_rel2": "",
        "obj2": "",
        "input_ent2": "belgium"
    },
    {
        "q3": "do you really think brazil could have beat france in this cup?",
        "a3": "in a series of 7 games, i think they would have defeated belgium and went on to win the world cup.",
        "kgER3": {
            "brazil": [
                "coach",
                "captain",
                "world cup appearance",
                "number of world cup champion",
                "world cup Champions",
                "goalkeeper",
                "has player",
                "defender",
                "midfielder",
                "forward"
            ],
            "belgium": [
                "coach",
                "captain",
                "world cup appearance",
                "number of world cup champion",
                "world cup Third place",
                "goalkeeper",
                "has player",
                "defender",
                "midfielder",
                "forward"
            ],
            "france": [
                "coach",
                "captain",
                "world cup appearance",
                "number of world cup champion",
                "world cup Champions",
                "goalkeeper",
                "has player",
                "defender",
                "midfielder",
                "forward"
            ]
        },
        "a3_skt": "in a series of @object games, i think they would have defeated @entity and went on to win the world cup.",
        "a3_v2": "in a series of 7 games, i think they would have defeated belgium and went on to win the world cup.",
        "corr_rel3": "",
        "obj3": "",
        "input_ent3": "france"
    },
    {
        "q4": "were they annoyed to be kicked out of the world cup?",
        "a4": "i should think so. i know i would be",
        "kgER4": {
            "brazil": [
                "coach",
                "captain",
                "world cup appearance",
                "number of world cup champion",
                "world cup Champions",
                "goalkeeper",
                "has player",
                "defender",
                "midfielder",
                "forward"
            ],
            "belgium": [
                "coach",
                "captain",
                "world cup appearance",
                "number of world cup champion",
                "world cup Third place",
                "goalkeeper",
                "has player",
                "defender",
                "midfielder",
                "forward"
            ],
            "france": [
                "coach",
                "captain",
                "world cup appearance",
                "number of world cup champion",
                "world cup Champions",
                "goalkeeper",
                "has player",
                "defender",
                "midfielder",
                "forward"
            ]
        },
        "a4_skt": "i should think so. i know i would be",
        "a4_v2": "i should think so. i know i would be",
        "corr_rel4": "",
        "obj4": "",
        "input_ent4": "andres guardado"
    },
    {
        "q5": "do you think neymar is their best player?",
        "a5": "yes, but i hate him",
        "kgER5": {
            "brazil": [
                "coach",
                "captain",
                "world cup appearance",
                "number of world cup champion",
                "world cup Champions",
                "goalkeeper",
                "has player",
                "defender",
                "midfielder",
                "forward"
            ],
            "belgium": [
                "coach",
                "captain",
                "world cup appearance",
                "number of world cup champion",
                "world cup Third place",
                "goalkeeper",
                "has player",
                "defender",
                "midfielder",
                "forward"
            ],
            "france": [
                "coach",
                "captain",
                "world cup appearance",
                "number of world cup champion",
                "world cup Champions",
                "goalkeeper",
                "has player",
                "defender",
                "midfielder",
                "forward"
            ],
            "neymar": [
                "has player",
                "position",
                "goals",
                "caps",
                "age",
                "jersey",
                "height",
                "captain",
                "forward"
            ]
        },
        "a5_skt": "yes, but i hate him",
        "a5_v2": "yes, but i hate him",
        "corr_rel5": "",
        "obj5": "",
        "input_ent5": "neymar"
    }
]