[
    {
        "q1": "what is the weather next_week",
        "a1": "for which city would you like to know the weather for next_week",
        "input_rel1": "",
        "corr_rel1": "",
        "obj1": "",
        "input_ent1": "",
        "kvr_entlist_qa1": [
            "next_week"
        ]
    },
    {
        "q2": "find out if there will be clear_skies in exeter this week",
        "a2": "there will not be clear_skies in exeter this week",
        "input_rel2": "",
        "corr_rel2": "",
        "obj2": "",
        "input_ent2": "",
        "kvr_entlist_qa2": [
            "week",
            "exeter",
            "clear_skies"
        ]
    },
    {
        "q3": "thanks car",
        "a3": "not a problem",
        "input_rel3": "",
        "corr_rel3": "",
        "obj3": "",
        "input_ent3": "",
        "kvr_entlist_qa3": []
    }
]