[
    {
        "q1": "navigate to the nearest place to get coffee",
        "a1": "palo_alto_cafe is the nearest place to get coffee at 5_miles away at 436_alger_drive",
        "input_rel1": "",
        "corr_rel1": "",
        "obj1": "",
        "input_ent1": "",
        "kvr_entlist_qa1": [
            "5_miles",
            "palo_alto_cafe"
        ]
    },
    {
        "q2": "thanks",
        "a2": "you re welcome",
        "input_rel2": "",
        "corr_rel2": "",
        "obj2": "",
        "input_ent2": "",
        "kvr_entlist_qa2": []
    }
]