[
    {
        "q1": "i need tea",
        "a1": "i have a listing for a place that serves tea that is 2_miles away",
        "input_rel1": "",
        "corr_rel1": "",
        "obj1": "",
        "input_ent1": "coffee_or_tea_place",
        "kvr_entlist_qa1": [
            "2_miles"
        ]
    },
    {
        "q2": "what is the address",
        "a2": "coupa is located at 394_van_ness_ave",
        "input_rel2": "distance,poi,address,traffic_info,poi_type",
        "corr_rel2": "address",
        "obj2": "394_van_ness_ave",
        "input_ent2": "coupa",
        "kvr_entlist_qa2": [
            "394_van_ness_ave",
            "coupa"
        ]
    },
    {
        "q3": "sounds awesome thanks",
        "a3": "no problem",
        "input_rel3": "",
        "corr_rel3": "",
        "obj3": "",
        "input_ent3": "",
        "kvr_entlist_qa3": []
    },
    {
        "q4": "thanks again",
        "a4": "you re welcome",
        "input_rel4": "",
        "corr_rel4": "",
        "obj4": "",
        "input_ent4": "",
        "kvr_entlist_qa4": []
    }
]