[
    {
        "q1": "what is the date and time of my dentist_appointment",
        "a1": "for which one i have three one with your brother at 3pm on the_19th one with your sister at 10am on thursday and one with your father at 5pm on the_9th",
        "input_rel1": "time,party,date",
        "corr_rel1": "date,time,party",
        "obj1": "brother,10am,father,the_9th,5pm,the_19th,sister,3pm",
        "input_ent1": "dentist_appointment",
        "kvr_entlist_qa1": [
            "brother",
            "10am",
            "father",
            "the_9th",
            "5pm",
            "the_19th",
            "thursday",
            "sister",
            "3pm"
        ]
    },
    {
        "q2": "thanks that will do just fine",
        "a2": "you are welcome",
        "input_rel2": "",
        "corr_rel2": "",
        "obj2": "",
        "input_ent2": "",
        "kvr_entlist_qa2": []
    }
]